sag_py_auth/__init__.py
sag_py_auth/auth_context.py
sag_py_auth/jwt_auth.py
sag_py_auth/models.py
sag_py_auth/py.typed
sag_py_auth/token_decoder.py
sag_py_auth/user_name_logging_filter.py
sag_py_auth/utils.py
sag_py_auth-1.2.3.dist-info/licenses/LICENSE.txt
sag_py_auth-1.2.3.dist-info/METADATA
sag_py_auth-1.2.3.dist-info/WHEEL
sag_py_auth-1.2.3.dist-info/top_level.txt
sag_py_auth-1.2.3.dist-info/RECORD
