Metadata-Version: 2.4
Name: sag-py-auth
Version: 1.2.3
Summary: Keycloak authentication for python projects
Home-page: https://github.com/SamhammerAG/sag_py_auth
Author: Samhammer AG
Author-email: support@samhammer.de
License: MIT
Project-URL: Documentation, https://github.com/SamhammerAG/sag_py_auth
Project-URL: Bug Reports, https://github.com/SamhammerAG/sag_py_auth/issues
Project-URL: Source, https://github.com/SamhammerAG/sag_py_auth
Keywords: auth,fastapi,keycloak
Classifier: Programming Language :: Python :: 3
Classifier: License :: OSI Approved :: MIT License
Classifier: Operating System :: OS Independent
Classifier: Topic :: Software Development :: Libraries :: Python Modules
Classifier: Topic :: Software Development :: Libraries
Classifier: Topic :: Software Development
Requires-Python: >=3.12
License-File: LICENSE.txt
Requires-Dist: anyio>=4.9.0
Requires-Dist: cachetools>=6.0.0
Requires-Dist: contextvars>=2.4.0
Requires-Dist: cryptography==45.0.5
Requires-Dist: fastapi[standard]>=0.115.12
Requires-Dist: PyJWT>=2.10.1
Requires-Dist: starlette>=0.46.0
Requires-Dist: zipp>=3.21.0
Provides-Extra: dev
Requires-Dist: build; extra == "dev"
Requires-Dist: coverage-lcov; extra == "dev"
Requires-Dist: flake8; extra == "dev"
Requires-Dist: mock; extra == "dev"
Requires-Dist: mypy; extra == "dev"
Requires-Dist: pytest; extra == "dev"
Requires-Dist: pytest-asyncio; extra == "dev"
Requires-Dist: pytest-cov; extra == "dev"
Requires-Dist: types-cachetools; extra == "dev"
Requires-Dist: types-mock; extra == "dev"
Requires-Dist: types-requests>=2.32.0; extra == "dev"
Requires-Dist: tomli; extra == "dev"
Dynamic: author
Dynamic: author-email
Dynamic: classifier
Dynamic: description
Dynamic: description-content-type
Dynamic: home-page
Dynamic: keywords
Dynamic: license
Dynamic: license-file
Dynamic: project-url
Dynamic: provides-extra
Dynamic: requires-dist
Dynamic: requires-python
Dynamic: summary
